odoo10_addon_stock_cancel_delivery-10.0.0.1.0.99.dev5-py2.7-nspkg.pth
odoo/addons/stock_cancel_delivery/README.rst
odoo/addons/stock_cancel_delivery/__init__.py
odoo/addons/stock_cancel_delivery/__manifest__.py
odoo/addons/stock_cancel_delivery/i18n/pt.po
odoo/addons/stock_cancel_delivery/i18n/stock_cancel_delivery.pot
odoo/addons/stock_cancel_delivery/models/__init__.py
odoo/addons/stock_cancel_delivery/models/sale_order_line.py
odoo/addons/stock_cancel_delivery/models/stock_picking.py
odoo/addons/stock_cancel_delivery/static/description/icon.png
odoo/addons/stock_cancel_delivery/tests/__init__.py
odoo/addons/stock_cancel_delivery/tests/test_stock_cancel_delivery.py
odoo10_addon_stock_cancel_delivery-10.0.0.1.0.99.dev5.dist-info/METADATA
odoo10_addon_stock_cancel_delivery-10.0.0.1.0.99.dev5.dist-info/RECORD
odoo10_addon_stock_cancel_delivery-10.0.0.1.0.99.dev5.dist-info/WHEEL
odoo10_addon_stock_cancel_delivery-10.0.0.1.0.99.dev5.dist-info/namespace_packages.txt
odoo10_addon_stock_cancel_delivery-10.0.0.1.0.99.dev5.dist-info/top_level.txt
